aemessenger/__init__.py
aemessenger/gui_client.py
aemessenger/server.py
aemessenger/Client/__init__.py
aemessenger/Client/app.client.log
aemessenger/Client/clientDany.sqlite
aemessenger/Client/clientcontroller.py
aemessenger/Client/clientstorage.py
aemessenger/Client/clienttestlogin.sqlite
aemessenger/Client/socketclient.py
aemessenger/Img/__init__.py
aemessenger/Img/user.png
aemessenger/Img/user_new_msg.png
aemessenger/JIM/__init__.py
aemessenger/JIM/jimmsg.py
aemessenger/JIM/jimresponse.py
aemessenger/Log/__init__.py
aemessenger/Log/app.client.log
aemessenger/Log/app.server.log
aemessenger/Log/log_config.py
aemessenger/Server/__init__.py
aemessenger/Server/server.sqlite
aemessenger/Server/servercontroller.py
aemessenger/Server/serverstorage.py
aemessenger/UI/__init__.py
aemessenger/UI/add_contact_dialog.py
aemessenger/UI/client.ui
aemessenger/UI/username_dialog.py
aemessenger-0.1.7.dist-info/DESCRIPTION.rst
aemessenger-0.1.7.dist-info/METADATA
aemessenger-0.1.7.dist-info/RECORD
aemessenger-0.1.7.dist-info/WHEEL
aemessenger-0.1.7.dist-info/entry_points.txt
aemessenger-0.1.7.dist-info/metadata.json
aemessenger-0.1.7.dist-info/top_level.txt
