Metadata-Version: 2.0
Name: aemessenger
Version: 0.1.7
Summary: A sample Python socket messenger
Home-page: https://github.com/danyae/PythonMessenger
Author: Dany ae
Author-email: noreply@aetech.ru
License: GPL
Keywords: sample messenger chat socket geekbrains
Platform: UNKNOWN
Classifier: Development Status :: 3 - Alpha
Classifier: Intended Audience :: Developers
Classifier: Topic :: Communications :: Chat :: Internet Relay Chat
Classifier: License :: OSI Approved :: GNU General Public License v3 (GPLv3)
Classifier: Programming Language :: Python :: 3.4
Classifier: Programming Language :: Python :: 3.5
Classifier: Programming Language :: Python :: 3.6
Requires-Dist: PyQt5 (>=5.9)
Requires-Dist: SQLAlchemy (>=1.1.14)
Requires-Dist: Pillow (>=4.3.0)
